{"cameraMode":{"drawMode":0,"name":"Shaded","section":"Shading Mode"},"sceneLighting":false,"audioPlay":false,"sceneViewState":{"m_AlwaysRefresh":true,"showFog":true,"showSkybox":false,"showFlares":true,"showImageEffects":false,"showParticleSystems":true,"showVisualEffectGraphs":true,"m_FxEnabled":true},"in2DMode":false,"pivot":{"x":1.284409999847412,"y":1.7463366985321046,"z":-0.9799470901489258},"rotation":{"x":0.07452206313610077,"y":0.8673070073127747,"z":-0.13668446242809297,"w":0.4728727638721466},"size":3.673909902572632,"orthographic":false}